ci/__init__.py
ci/ci.py
ci/git.py
ci_py-1.0.0.dist-info/LICENSE
ci_py-1.0.0.dist-info/METADATA
ci_py-1.0.0.dist-info/WHEEL
ci_py-1.0.0.dist-info/top_level.txt
ci_py-1.0.0.dist-info/RECORD
