Metadata-Version: 2.1
Name: ci-py
Version: 1.0.0
Summary: Python toolkit for working with Continuous Integration services.
Home-page: https://github.com/grantmcconnaughey/ci.py
Author: Grant McConnaughey
Author-email: grantmcconnaughey@gmail.com
License: MIT
Keywords: ci
Platform: UNKNOWN
Classifier: Development Status :: 5 - Production/Stable
Classifier: Intended Audience :: Developers
Classifier: License :: OSI Approved :: MIT License
Classifier: Natural Language :: English
Classifier: Programming Language :: Python
Classifier: Programming Language :: Python :: 2
Classifier: Programming Language :: Python :: 2.7
Classifier: Programming Language :: Python :: 3
Classifier: Programming Language :: Python :: 3.5
Classifier: Programming Language :: Python :: 3.6
Classifier: Programming Language :: Python :: 3.7
Classifier: Programming Language :: Python :: 3.8
